typeid_field/__init__.py
typeid_field/fields.py
django_typeid_field-0.0.1.dist-info/LICENCE
django_typeid_field-0.0.1.dist-info/METADATA
django_typeid_field-0.0.1.dist-info/WHEEL
django_typeid_field-0.0.1.dist-info/top_level.txt
django_typeid_field-0.0.1.dist-info/RECORD
