Metadata-Version: 2.1
Name: django-typeid-field
Version: 0.0.1
Summary: TypeID Field for Django
Author-email: mschfh <mschfh@proton.me>
License: MIT
Project-URL: Homepage, https://github.com/mschfh/django-typeid-field
Project-URL: Documentation, https://github.com/mschfh/django-typeid-field
Project-URL: Repository, https://github.com/mschfh/django-typeid-field.git
Keywords: django,typeid,django-field
Classifier: Development Status :: 4 - Beta
Classifier: Environment :: Web Environment
Classifier: Framework :: Django
Classifier: License :: OSI Approved :: MIT License
Classifier: Operating System :: OS Independent
Classifier: Programming Language :: Python
License-File: LICENCE
Requires-Dist: typeid-python
Requires-Dist: django >=2
